{"total":665,"pageSize":12,"pageCount":56,"data":[{"title":"普通用户使用SUDO安装程序","uid":"440f944a15eacd750d61d670fceb563d","slug":"old_topic/2016-09-17-130","date":"2016-09-17T14:50:18.000Z","updated":"2024-03-14T06:15:59.734Z","comments":true,"path":"api/articles/old_topic/2016-09-17-130.json","cover":null,"text":"1.添加用户 可以用adduser和useradd来添加用户，用userdel来删除用户。 最简单的命令： 1sudo adduser test 会自动同名组，创建/home/test/，从etc/skel/复制文件，并设定密码和相关初始身份信息 原始一点的命令： 12sudo ...","link":"","photos":[],"count_time":{"symbolsCount":764,"symbolsTime":"1 mins."},"categories":[{"name":"topic","slug":"topic","count":308,"path":"api/categories/topic.json"}],"tags":[{"name":"lua","slug":"lua","count":153,"path":"api/tags/lua.json"}],"author":{"name":"安全书","slug":"blog-author","avatar":"https://img-blog.csdnimg.cn/20210313122054101.png","link":"/","description":"《墨守之道-Web服务安全架构与实践》","socials":{"github":"https://github.com/shengnoah","twitter":"","stackoverflow":"","wechat":"","qq":"","weibo":"https://weibo.com/u/3732639263","zhihu":"https://www.zhihu.com/people/openresty","csdn":"","juejin":"","customs":{}}}},{"title":"LUA通过授权方式登录Redis","uid":"d4821869c1f22a5f8395c793ca14a30c","slug":"old_topic/2016-09-17-131","date":"2016-09-17T14:50:18.000Z","updated":"2024-03-14T06:15:59.735Z","comments":true,"path":"api/articles/old_topic/2016-09-17-131.json","cover":null,"text":"作者：糖果 123456789101112require &quot;redis&quot;local redis = require &#x27;redis&#x27;local client = redis.connect(&#x27;127.0.0.1&#x27;, 637...","link":"","photos":[],"count_time":{"symbolsCount":265,"symbolsTime":"1 mins."},"categories":[{"name":"topic","slug":"topic","count":308,"path":"api/categories/topic.json"}],"tags":[{"name":"lua","slug":"lua","count":153,"path":"api/tags/lua.json"}],"author":{"name":"安全书","slug":"blog-author","avatar":"https://img-blog.csdnimg.cn/20210313122054101.png","link":"/","description":"《墨守之道-Web服务安全架构与实践》","socials":{"github":"https://github.com/shengnoah","twitter":"","stackoverflow":"","wechat":"","qq":"","weibo":"https://weibo.com/u/3732639263","zhihu":"https://www.zhihu.com/people/openresty","csdn":"","juejin":"","customs":{}}}},{"title":"LUA如何遍历返回的JSON数据","uid":"222b2df1d56a571ace7dc7573b0f68fd","slug":"old_topic/2016-09-17-132","date":"2016-09-17T14:50:18.000Z","updated":"2024-03-14T06:15:59.735Z","comments":true,"path":"api/articles/old_topic/2016-09-17-132.json","cover":null,"text":"作者：糖果 代码如下： 12345678910111213141516171819202122232425function get_json_key(key) if not key then return end local json_var = client:get(key) ...","link":"","photos":[],"count_time":{"symbolsCount":"1.1k","symbolsTime":"1 mins."},"categories":[{"name":"topic","slug":"topic","count":308,"path":"api/categories/topic.json"}],"tags":[{"name":"lua","slug":"lua","count":153,"path":"api/tags/lua.json"},{"name":"lua json","slug":"lua-json","count":1,"path":"api/tags/lua-json.json"},{"name":"lua循环","slug":"lua循环","count":1,"path":"api/tags/lua循环.json"},{"name":"lua循环遍历","slug":"lua循环遍历","count":1,"path":"api/tags/lua循环遍历.json"}],"author":{"name":"安全书","slug":"blog-author","avatar":"https://img-blog.csdnimg.cn/20210313122054101.png","link":"/","description":"《墨守之道-Web服务安全架构与实践》","socials":{"github":"https://github.com/shengnoah","twitter":"","stackoverflow":"","wechat":"","qq":"","weibo":"https://weibo.com/u/3732639263","zhihu":"https://www.zhihu.com/people/openresty","csdn":"","juejin":"","customs":{}}}},{"title":"关于 OPENRESTY 的两三事","uid":"a924894efc1b5c05addcec2e153c3f2f","slug":"old_topic/2016-09-17-135","date":"2016-09-17T14:50:18.000Z","updated":"2024-03-14T06:15:59.735Z","comments":true,"path":"api/articles/old_topic/2016-09-17-135.json","cover":null,"text":"编辑：糖果 基础原理Nginx 采用的是 master-worker 模型，一个 master 进程管理多个 worker 进程，基本的事件处理都是放在 woker 中，master 负责一些全局初始化，以及对 worker 的管理。 每个 woker 使用一个 LuaVM，当请...","link":"","photos":[],"count_time":{"symbolsCount":"11k","symbolsTime":"10 mins."},"categories":[{"name":"topic","slug":"topic","count":308,"path":"api/categories/topic.json"}],"tags":[{"name":"lua","slug":"lua","count":153,"path":"api/tags/lua.json"}],"author":{"name":"安全书","slug":"blog-author","avatar":"https://img-blog.csdnimg.cn/20210313122054101.png","link":"/","description":"《墨守之道-Web服务安全架构与实践》","socials":{"github":"https://github.com/shengnoah","twitter":"","stackoverflow":"","wechat":"","qq":"","weibo":"https://weibo.com/u/3732639263","zhihu":"https://www.zhihu.com/people/openresty","csdn":"","juejin":"","customs":{}}}},{"title":"OPENRESTY 中的简易HTTP加密","uid":"ceeda26fcc5b2c890a2ed530be0ef341","slug":"old_topic/2016-09-17-136","date":"2016-09-17T14:50:18.000Z","updated":"2024-03-14T06:15:59.735Z","comments":true,"path":"api/articles/old_topic/2016-09-17-136.json","cover":null,"text":"需求速度快；可逆；容易实现，不存在语言障碍；思考将一个任意内容的字符串作为密钥，从明文中取等长字符串，逐字节将明文和密钥进行异或计算，得到密文。循环处理整个明文，得到完整密文。对密文进行同样的运算即可解密。 算法 123456789101112131415161718192021...","link":"","photos":[],"count_time":{"symbolsCount":"1.5k","symbolsTime":"1 mins."},"categories":[{"name":"topic","slug":"topic","count":308,"path":"api/categories/topic.json"}],"tags":[{"name":"lua","slug":"lua","count":153,"path":"api/tags/lua.json"}],"author":{"name":"安全书","slug":"blog-author","avatar":"https://img-blog.csdnimg.cn/20210313122054101.png","link":"/","description":"《墨守之道-Web服务安全架构与实践》","socials":{"github":"https://github.com/shengnoah","twitter":"","stackoverflow":"","wechat":"","qq":"","weibo":"https://weibo.com/u/3732639263","zhihu":"https://www.zhihu.com/people/openresty","csdn":"","juejin":"","customs":{}}}},{"title":"NGINX配置初始化过程","uid":"e77113c5554b3f904d7fab1c518f6770","slug":"old_topic/2016-09-17-134","date":"2016-09-17T14:50:18.000Z","updated":"2024-03-14T06:15:59.735Z","comments":true,"path":"api/articles/old_topic/2016-09-17-134.json","cover":[],"text":"nginx解析配置文件，将解析出来得配置存放在ngx_cycle_s的conf_ctx中，conf_ctx是个四级指针，因为保存这些配置需要context，而这些context是有层级关系，最终的配置结构如图： 图片：27767798_1370416906jegE.png htt...","link":"","photos":[],"count_time":{"symbolsCount":"4.6k","symbolsTime":"4 mins."},"categories":[{"name":"topic","slug":"topic","count":308,"path":"api/categories/topic.json"}],"tags":[{"name":"lua","slug":"lua","count":153,"path":"api/tags/lua.json"}],"author":{"name":"安全书","slug":"blog-author","avatar":"https://img-blog.csdnimg.cn/20210313122054101.png","link":"/","description":"《墨守之道-Web服务安全架构与实践》","socials":{"github":"https://github.com/shengnoah","twitter":"","stackoverflow":"","wechat":"","qq":"","weibo":"https://weibo.com/u/3732639263","zhihu":"https://www.zhihu.com/people/openresty","csdn":"","juejin":"","customs":{}}}},{"title":"如何在SAE上架设RPC服务与Openresty的Lua服务通信","uid":"1c16f4ddd5c0935af18ce72063de0291","slug":"old_topic/2016-09-17-123","date":"2016-09-17T14:50:18.000Z","updated":"2024-03-14T06:15:59.734Z","comments":true,"path":"api/articles/old_topic/2016-09-17-123.json","cover":null,"text":"作者：糖果 有时候我们写的服务可能会部署到很同种不同类型的服务器上，有一些数据，可能不便于存在本地，需要一个数据中心，保存这些数据。 我们要求是这样的： 1．客户端服务要周期性的去服务器上拉取数据。（存在SAE MySQL中）。 2．不使用长连接的方式通信，使用基于HTTP的协议...","link":"","photos":[],"count_time":{"symbolsCount":"4.5k","symbolsTime":"4 mins."},"categories":[{"name":"topic","slug":"topic","count":308,"path":"api/categories/topic.json"}],"tags":[{"name":"lua","slug":"lua","count":153,"path":"api/tags/lua.json"}],"author":{"name":"安全书","slug":"blog-author","avatar":"https://img-blog.csdnimg.cn/20210313122054101.png","link":"/","description":"《墨守之道-Web服务安全架构与实践》","socials":{"github":"https://github.com/shengnoah","twitter":"","stackoverflow":"","wechat":"","qq":"","weibo":"https://weibo.com/u/3732639263","zhihu":"https://www.zhihu.com/people/openresty","csdn":"","juejin":"","customs":{}}}},{"title":"最简单的LUA随机数生成","uid":"cbbd7e228645caa3cfb0dd345f9fe075","slug":"old_topic/2016-09-17-139","date":"2016-09-17T14:50:18.000Z","updated":"2024-03-14T06:15:59.735Z","comments":true,"path":"api/articles/old_topic/2016-09-17-139.json","cover":null,"text":"[code]math.randomseed(os.time())for i=1, 5 do print(math.random())end [/code] ","link":"","photos":[],"count_time":{"symbolsCount":78,"symbolsTime":"1 mins."},"categories":[{"name":"topic","slug":"topic","count":308,"path":"api/categories/topic.json"}],"tags":[{"name":"lua","slug":"lua","count":153,"path":"api/tags/lua.json"}],"author":{"name":"安全书","slug":"blog-author","avatar":"https://img-blog.csdnimg.cn/20210313122054101.png","link":"/","description":"《墨守之道-Web服务安全架构与实践》","socials":{"github":"https://github.com/shengnoah","twitter":"","stackoverflow":"","wechat":"","qq":"","weibo":"https://weibo.com/u/3732639263","zhihu":"https://www.zhihu.com/people/openresty","csdn":"","juejin":"","customs":{}}}},{"title":"Python的List和C++的Vector的对比","uid":"62ab39d0bc32c5ce1245ceed42efb629","slug":"old_topic/2016-09-17-14","date":"2016-09-17T14:50:18.000Z","updated":"2024-03-14T06:15:59.735Z","comments":true,"path":"api/articles/old_topic/2016-09-17-14.json","cover":null,"text":"作者：糖果 简单的对比了一下Python的List和C++的Vector操作，用Python代替C++的注释。 另外推荐一个在线的编译器，codepad.org。 1.定义数据 Python 1candyList = [&quot;Red Candy&quot;, &quot;G...","link":"","photos":[],"count_time":{"symbolsCount":"3k","symbolsTime":"3 mins."},"categories":[{"name":"topic","slug":"topic","count":308,"path":"api/categories/topic.json"}],"tags":[{"name":"lua","slug":"lua","count":153,"path":"api/tags/lua.json"}],"author":{"name":"安全书","slug":"blog-author","avatar":"https://img-blog.csdnimg.cn/20210313122054101.png","link":"/","description":"《墨守之道-Web服务安全架构与实践》","socials":{"github":"https://github.com/shengnoah","twitter":"","stackoverflow":"","wechat":"","qq":"","weibo":"https://weibo.com/u/3732639263","zhihu":"https://www.zhihu.com/people/openresty","csdn":"","juejin":"","customs":{}}}},{"title":"Openresty的ngx_http_lua_balancer代码下载","uid":"d52502bd5958725397262906a370cd45","slug":"old_topic/2016-09-17-140","date":"2016-09-17T14:50:18.000Z","updated":"2024-03-14T06:15:59.735Z","comments":true,"path":"api/articles/old_topic/2016-09-17-140.json","cover":null,"text":"Openresty代码下载，已经替换过了ngx_http_lua_balancer模块： 点击链接下载： ","link":"","photos":[],"count_time":{"symbolsCount":53,"symbolsTime":"1 mins."},"categories":[{"name":"topic","slug":"topic","count":308,"path":"api/categories/topic.json"}],"tags":[{"name":"lua","slug":"lua","count":153,"path":"api/tags/lua.json"}],"author":{"name":"安全书","slug":"blog-author","avatar":"https://img-blog.csdnimg.cn/20210313122054101.png","link":"/","description":"《墨守之道-Web服务安全架构与实践》","socials":{"github":"https://github.com/shengnoah","twitter":"","stackoverflow":"","wechat":"","qq":"","weibo":"https://weibo.com/u/3732639263","zhihu":"https://www.zhihu.com/people/openresty","csdn":"","juejin":"","customs":{}}}},{"title":"LUA FAQ","uid":"a7f454cd8b8cc1ba699e660a76d25326","slug":"old_topic/2016-09-17-133","date":"2016-09-17T14:50:18.000Z","updated":"2024-03-14T06:15:59.735Z","comments":true,"path":"api/articles/old_topic/2016-09-17-133.json","cover":null,"text":"LUA FAQ Lua判断空表的正确姿势 Lua中ipair和pair关键字的区别是什么？ Lua的转义符号“%” Nginx用户权限(文件读写时候应该注意到的问题) 关于 OPENRESTY 的两三事 NGINX配置初始化过程 OPENRESTY 中的简易HTTP加密 ","link":"","photos":[],"count_time":{"symbolsCount":143,"symbolsTime":"1 mins."},"categories":[{"name":"topic","slug":"topic","count":308,"path":"api/categories/topic.json"}],"tags":[{"name":"lua","slug":"lua","count":153,"path":"api/tags/lua.json"}],"author":{"name":"安全书","slug":"blog-author","avatar":"https://img-blog.csdnimg.cn/20210313122054101.png","link":"/","description":"《墨守之道-Web服务安全架构与实践》","socials":{"github":"https://github.com/shengnoah","twitter":"","stackoverflow":"","wechat":"","qq":"","weibo":"https://weibo.com/u/3732639263","zhihu":"https://www.zhihu.com/people/openresty","csdn":"","juejin":"","customs":{}}}},{"title":"Windows版本的Openresty文件下载","uid":"1c4e1c2d58b108caf66093510a587e9f","slug":"old_topic/2016-09-17-141","date":"2016-09-17T14:50:18.000Z","updated":"2024-03-14T06:15:59.735Z","comments":true,"path":"api/articles/old_topic/2016-09-17-141.json","cover":null,"text":"openresty for windows32位 openresty for windows64位 ","link":"","photos":[],"count_time":{"symbolsCount":51,"symbolsTime":"1 mins."},"categories":[{"name":"topic","slug":"topic","count":308,"path":"api/categories/topic.json"}],"tags":[],"author":{"name":"安全书","slug":"blog-author","avatar":"https://img-blog.csdnimg.cn/20210313122054101.png","link":"/","description":"《墨守之道-Web服务安全架构与实践》","socials":{"github":"https://github.com/shengnoah","twitter":"","stackoverflow":"","wechat":"","qq":"","weibo":"https://weibo.com/u/3732639263","zhihu":"https://www.zhihu.com/people/openresty","csdn":"","juejin":"","customs":{}}}}]}